mocktime/__init__.py
mocktime/_datetime.py
mocktime/_grpc.py
mocktime/_loguru.py
mocktime/_process.py
mocktime/_time.py
mocktime/_version.py
mocktime/unsafe_magic.py
mocktime-0.3.1.dist-info/LICENSE
mocktime-0.3.1.dist-info/METADATA
mocktime-0.3.1.dist-info/WHEEL
mocktime-0.3.1.dist-info/top_level.txt
mocktime-0.3.1.dist-info/RECORD
