Metadata-Version: 2.1
Name: mocktime
Version: 0.3.1
Summary: patch to mock time and datetime
Author-email: wukan <wu-kan@163.com>
License: BSD-3-Clause
Keywords: mock,datetime,apscheduler,schedule
Classifier: Development Status :: 4 - Beta
Classifier: Programming Language :: Python
Requires-Python: >=3.7
License-File: LICENSE
